{
  "sections": [
    {
      "type": "breadcrumbs",
      "enabled": true
    },
    {
      "type": "offers-timer",
      "max_hours": 1,
      "start": "2022-12-28T00:10:35.790Z",
      "end": "2023-02-01T00:10:35.839Z",
      "offers": [
        "6331e10b73321213f88e269f",
        "6331e2e373321213f88e2c9e",
        "63ac990d4834634f73222a8b"
      ],
      "notes": "Aproveite! pois a qualquer momento essa oferta sai do ar."
    },
    {
      "type": "product-block",
      "enabled": true,
      "size_guide": {
        "image": "",
        "title": ""
      }
    },
    {
      "type": "related-products",
      "title": "Produtos relacionados"
    },
    {
      "type": "recommended-products",
      "title": "Quem comprou este produto, também comprou:"
    },
    {
      "type": "product-description",
      "enabled": true
    },
    {
      "type": "product-specifications",
      "enabled": true
    },
    {
      "type": "blog",
      "enabled": true
    },
    {
      "type": "banners-grid",
      "banners": [
        {
          "img": "/img/uploads/euronutry.png"
        }
      ]
    },
    {
      "type": "dynamic-showcase",
      "load_more": true,
      "sort": "offers"
    },
    {
      "type": "brands-carousel",
      "limit": 24,
      "offset": 0,
      "sort": "name",
      "autoplay": 2000
    }
  ]
}